[
  {
    "index": 0,
    "language": "pl",
    "restaurant": "demo",
    "section": "PRZYSTAWKI",
    "dishName": "Tatar wołowy",
    "dishDescription": "Z cebulką, ogórkiem kiszonym, grzybkami i żółtkiem, podany z pieczywem",
    "dishVariantPrice": 25,
    "dishVariantName": ""
  },
  {
    "index": 1,
    "language": "pl",
    "restaurant": "demo",
    "section": "PRZYSTAWKI",
    "dishName": "Nachosy po meksykańsku",
    "dishDescription": "Podane z duszną wołowiną",
    "dishVariantPrice": 12,
    "dishVariantName": ""
  },
  {
    "index": 2,
    "language": "pl",
    "restaurant": "demo",
    "section": "ZUPY",
    "dishName": "Flaki wołowe",
    "dishDescription": "Według rodzinnego przepisu",
    "dishVariantPrice": 13,
    "dishVariantName": ""
  },
  {
    "index": 3,
    "language": "pl",
    "restaurant": "demo",
    "section": "ZUPY",
    "dishName": "Barszcz czerwony",
    "dishDescription": "Podany z mięsnym krokietem",
    "dishVariantPrice": 16,
    "dishVariantName": ""
  },
  {
    "index": 4,
    "language": "pl",
    "restaurant": "demo",
    "section": "DANIA GŁÓWNE",
    "dishName": "Pstrąg z pieca",
    "dishDescription": "Podany z grillowanymi warzywami",
    "dishVariantPrice": 35,
    "dishVariantName": ""
  },
  {
    "index": 5,
    "language": "pl",
    "restaurant": "demo",
    "section": "DANIA GŁÓWNE",
    "dishName": "Pierogi - 10 szt.",
    "dishVariantPrice": 14,
    "dishVariantName": "z kapustą i grzybami"
  },
  {
    "index": 6,
    "language": "pl",
    "restaurant": "demo",
    "section": "DANIA GŁÓWNE",
    "dishName": "Pierogi - 10 szt.",
    "dishVariantPrice": 14,
    "dishVariantName": "z mięsem"
  }
]
